ktch/__init__.py
ktch/datasets/__init__.py
ktch/datasets/_base.py
ktch/datasets/_sample_generator.py
ktch/datasets/data/__init__.py
ktch/datasets/data/data_landmark_mosquito_wings.csv
ktch/datasets/data/data_outline_bottles.csv
ktch/datasets/data/data_outline_mosquito_wings.csv
ktch/datasets/data/meta_landmark_mosquito_wings.csv
ktch/datasets/data/meta_outline_bottles.csv
ktch/datasets/data/meta_outline_mosquito_wings.csv
ktch/datasets/data/test_coef_nharm_6_norm_false_outline_bottles.csv
ktch/datasets/data/test_coef_nharm_6_norm_true_outline_bottles.csv
ktch/datasets/descr/__init__.py
ktch/datasets/descr/data_landmark_mosquito_wings.rst
ktch/datasets/descr/data_outline_bottles.rst
ktch/datasets/descr/data_outline_mosquito_wings.rst
ktch/harmonic/__init__.py
ktch/harmonic/_elliptic_Fourier_analysis.py
ktch/harmonic/_spherical_harmonic_analysis.py
ktch/harmonic/tests/__init__.py
ktch/harmonic/tests/test_elliptic_Fourier_analysis.py
ktch/harmonic/tests/test_spherical_harmonic_analysis.py
ktch/io/_SPHARM_PDM.py
ktch/io/__init__.py
ktch/io/_chc.py
ktch/io/_tps.py
ktch/io/tests/test_SPHARM_PDM.py
ktch/io/tests/test_chc.py
ktch/io/tests/test_chc_coordinates.py
ktch/io/tests/test_tps.py
ktch/io/tests/data/andesred_07_allSegments_SPHARM.coef
ktch/io/tests/data/landmarks_triangle.tps
ktch/io/tests/data/sample_curve_data.tps
ktch/landmark/_Procrustes_analysis.py
ktch/landmark/__init__.py
ktch/landmark/_kriging.py
ktch/landmark/_landmark.py
ktch/landmark/_plot/__init__.py
ktch/landmark/_plot/_tps.py
ktch/landmark/tests/__init__.py
ktch/landmark/tests/test_Procrustes_analysis.py
ktch/motion/__init__.py
ktch/outline/__init__.py
ktch/plot/__init__.py
ktch/plot/_kriging.py
ktch/plot/_pca.py
ktch/tests/__init__.py
ktch-0.6.1.dist-info/METADATA
ktch-0.6.1.dist-info/WHEEL
ktch-0.6.1.dist-info/licenses/LICENSE
ktch-0.6.1.dist-info/RECORD
