Metadata-Version: 2.4
Name: ktch
Version: 0.6.1
Summary: ktch is a python package for model-based morphometrics.
Project-URL: Homepage, https://doc.ktch.dev
Project-URL: Repository, https://github.com/noshita/ktch
Author-email: "Noshita, Koji" <noshita@morphometrics.jp>
License:                                  Apache License
License-File: LICENSE
Keywords: morphometrics,theoretical morphology
Classifier: Intended Audience :: Developers
Classifier: Intended Audience :: Science/Research
Classifier: License :: OSI Approved :: Apache Software License
Classifier: Operating System :: MacOS
Classifier: Operating System :: Microsoft :: Windows
Classifier: Operating System :: POSIX
Classifier: Operating System :: Unix
Classifier: Programming Language :: Python
Classifier: Programming Language :: Python :: 3.11
Classifier: Topic :: Scientific/Engineering
Classifier: Topic :: Software Development
Requires-Python: >=3.11
Requires-Dist: numpy>=1.20
Requires-Dist: pandas[pyarrow]>=2.1
Requires-Dist: scikit-learn>=1.5
Requires-Dist: scipy>=1.7
Provides-Extra: docs
Provides-Extra: plot
Requires-Dist: matplotlib>=3.10.7; extra == 'plot'
Requires-Dist: plotly<6.0; extra == 'plot'
Requires-Dist: seaborn>=0.13.2; extra == 'plot'
